git_commit_message/__init__.py
git_commit_message/__main__.py
git_commit_message/_cli.py
git_commit_message/_gemini.py
git_commit_message/_git.py
git_commit_message/_gpt.py
git_commit_message/_llm.py
git_commit_message/_ollama.py
git_commit_message-0.8.1.dist-info/METADATA
git_commit_message-0.8.1.dist-info/WHEEL
git_commit_message-0.8.1.dist-info/entry_points.txt
git_commit_message-0.8.1.dist-info/top_level.txt
git_commit_message-0.8.1.dist-info/RECORD
