Metadata-Version: 2.4
Name: git-commit-message
Version: 0.8.1
Summary: Generate Git commit messages from staged changes using LLM
Maintainer-email: Mina Her <minacle@live.com>
License: This is free and unencumbered software released into the public domain.
Project-URL: Homepage, https://github.com/minacle/git-commit-message
Project-URL: Repository, https://github.com/minacle/git-commit-message
Project-URL: Issues, https://github.com/minacle/git-commit-message/issues
Classifier: Development Status :: 3 - Alpha
Classifier: Environment :: Console
Classifier: Intended Audience :: Developers
Classifier: License :: OSI Approved :: The Unlicense (Unlicense)
Classifier: Operating System :: OS Independent
Classifier: Programming Language :: Python
Classifier: Programming Language :: Python :: 3
Classifier: Programming Language :: Python :: 3 :: Only
Classifier: Programming Language :: Python :: 3.13
Classifier: Topic :: Software Development :: Version Control :: Git
Requires-Python: >=3.13
Requires-Dist: babel>=2.17.0
Requires-Dist: google-genai>=1.56.0
Requires-Dist: ollama>=0.4.0
Requires-Dist: openai>=2.6.1
Requires-Dist: tiktoken>=0.12.0
